kgextension/__init__.py
kgextension/caching_helper.py
kgextension/endpoints.py
kgextension/feature_selection.py
kgextension/feature_selection_helper.py
kgextension/feature_selection_sklearn.py
kgextension/fusion.py
kgextension/fusion_helper.py
kgextension/generator.py
kgextension/generator_helper.py
kgextension/generator_sklearn.py
kgextension/link_exploration.py
kgextension/link_exploration_sklearn.py
kgextension/linking.py
kgextension/linking_helper.py
kgextension/linking_sklearn.py
kgextension/schema_matching.py
kgextension/schema_matching_fusion_sklearn.py
kgextension/schema_matching_helper.py
kgextension/sparql_helper.py
kgextension/sparql_helper_helper.py
kgextension/uri_helper.py
kgextension/utilities.py
kgextension/utilities_helper.py
kgextension/utilities_sklearn.py
kgextension-0.1.1.dist-info/LICENSE.txt
kgextension-0.1.1.dist-info/METADATA
kgextension-0.1.1.dist-info/WHEEL
kgextension-0.1.1.dist-info/top_level.txt
kgextension-0.1.1.dist-info/RECORD
