Metadata-Version: 2.1
Name: kgextension
Version: 0.1.1
Summary: The kgextension allows to access and use Linked Open Data to augment existing datasets. 
Home-page: https://kgextension.readthedocs.io/en/latest/
Author: KG Team Uni Mannheim
Author-email: kgproject20@gmail.com
License: MIT
Project-URL: Source, https://github.com/om-hb/kgextension
Project-URL: Bug Reports, https://github.com/om-hb/kgextension/issues
Keywords: knowledge graph,linked open data,sparql
Platform: UNKNOWN
Classifier: License :: OSI Approved :: MIT License
Classifier: Programming Language :: Python :: 3
Classifier: Programming Language :: Python :: 3.4
Classifier: Programming Language :: Python :: 3.5
Classifier: Programming Language :: Python :: 3.6
Classifier: Programming Language :: Python :: 3.7
Requires-Dist: networkx
Requires-Dist: numpy
Requires-Dist: pandas (>=1.1.0)
Requires-Dist: info-gain
Requires-Dist: scikit-learn
Requires-Dist: tqdm
Requires-Dist: lxml
Requires-Dist: requests
Requires-Dist: pyspotlight
Requires-Dist: fuzzywuzzy
Requires-Dist: strsimpy
Requires-Dist: rdflib
Requires-Dist: deckar01-ratelimit
Requires-Dist: SPARQLWrapper
Requires-Dist: validators
